cfgrammar/__init__.py
cfgrammar/builder.py
cfgrammar/common.py
cfgrammar/examples.py
cfgrammar/grammar.py
cfgrammar/ll1.py
cfgrammar/semantic.py
cfgrammar/ui.py
cfgrammar/unrec.py
cfgrammar/utils.py
cfgrammar/lr/__init__.py
cfgrammar/lr/automaton.py
cfgrammar/lr/lalr.py
cfgrammar/lr/tables.py
cfgrammar-0.1.2.2.dist-info/LICENSE.TXT
cfgrammar-0.1.2.2.dist-info/METADATA
cfgrammar-0.1.2.2.dist-info/WHEEL
cfgrammar-0.1.2.2.dist-info/top_level.txt
cfgrammar-0.1.2.2.dist-info/RECORD
