Metadata-Version: 2.2
Name: cfgrammar
Version: 0.1.2.2
Summary: Context-free grammars and parsing
Author-email: Bruno Bogaert <Bruno.Bogaert@univ-lille.fr>
Maintainer-email: Bruno Bogaert <Bruno.Bogaert@univ-lille.fr>
Project-URL: Homepage, https://gitlab.univ-lille.fr/bruno.bogaert/cfgrammar
Project-URL: Repository, https://gitlab.univ-lille.fr/bruno.bogaert/cfgrammar
Classifier: Programming Language :: Python :: 3
Classifier: Operating System :: OS Independent
Classifier: License :: OSI Approved :: GNU General Public License v3 or later (GPLv3+)
Requires-Python: >=3.10
License-File: LICENSE.TXT
Requires-Dist: pandas
Requires-Dist: graphviz
